MANIFEST.in
README
setup.cfg
setup.py
PylonsTemplates/__init__.py
PylonsTemplates.egg-info/PKG-INFO
PylonsTemplates.egg-info/SOURCES.txt
PylonsTemplates.egg-info/dependency_links.txt
PylonsTemplates.egg-info/entry_points.txt
PylonsTemplates.egg-info/not-zip-safe
PylonsTemplates.egg-info/requires.txt
PylonsTemplates.egg-info/top_level.txt
PylonsTemplates/pylons_repoze_what/MANIFEST.in_tmpl
PylonsTemplates/pylons_repoze_what/README.txt_tmpl
PylonsTemplates/pylons_repoze_what/development.ini_tmpl
PylonsTemplates/pylons_repoze_what/ez_setup.py
PylonsTemplates/pylons_repoze_what/ez_setup.pyc
PylonsTemplates/pylons_repoze_what/setup.cfg_tmpl
PylonsTemplates/pylons_repoze_what/setup.py_tmpl
PylonsTemplates/pylons_repoze_what/test.ini_tmpl
PylonsTemplates/pylons_repoze_what/+package+/__init__.py_tmpl
PylonsTemplates/pylons_repoze_what/+package+/websetup.py_tmpl
PylonsTemplates/pylons_repoze_what/+package+/config/__init__.py_tmpl
PylonsTemplates/pylons_repoze_what/+package+/config/deployment.ini_tmpl_tmpl
PylonsTemplates/pylons_repoze_what/+package+/config/environment.py_tmpl
PylonsTemplates/pylons_repoze_what/+package+/config/middleware.py_tmpl
PylonsTemplates/pylons_repoze_what/+package+/config/routing.py_tmpl
PylonsTemplates/pylons_repoze_what/+package+/controllers/__init__.py_tmpl
PylonsTemplates/pylons_repoze_what/+package+/controllers/error.py_tmpl
PylonsTemplates/pylons_repoze_what/+package+/controllers/login.py_tmpl
PylonsTemplates/pylons_repoze_what/+package+/lib/__init__.py_tmpl
PylonsTemplates/pylons_repoze_what/+package+/lib/app_globals.py_tmpl
PylonsTemplates/pylons_repoze_what/+package+/lib/base.py_tmpl
PylonsTemplates/pylons_repoze_what/+package+/lib/helpers.py_tmpl
PylonsTemplates/pylons_repoze_what/+package+/model/__init__.py_tmpl
PylonsTemplates/pylons_repoze_what/+package+/model/auth.py_tmpl
PylonsTemplates/pylons_repoze_what/+package+/model/meta.py_tmpl
PylonsTemplates/pylons_repoze_what/+package+/public/bg.png
PylonsTemplates/pylons_repoze_what/+package+/public/favicon.ico
PylonsTemplates/pylons_repoze_what/+package+/public/index.html_tmpl
PylonsTemplates/pylons_repoze_what/+package+/public/pylons-logo.gif
PylonsTemplates/pylons_repoze_what/+package+/templates/.distutils_placeholder
