Metadata-Version: 1.0
Name: PylonsTemplates
Version: 0.1dev
Summary: Extra paster templates for Pylons including repoze.what implementation
Home-page: http://countergram.com/software/PylonsTemplates
Author: Jason Stitt
Author-email: jason@countergram.com
License: MIT
Platform: UNKNOWN
Classifier: Development Status :: 3 - Alpha
Classifier: Environment :: Console
Classifier: Framework :: Pylons
Classifier: Framework :: Paste
Classifier: Intended Audience :: Developers
Classifier: License :: OSI Approved :: MIT License
Classifier: Natural Language :: English
Classifier: Operating System :: OS Independent
Classifier: Programming Language :: Python :: 2
Classifier: Topic :: Internet :: WWW/HTTP
Classifier: Topic :: Utilities
